ambientmeta/__init__.py
ambientmeta/client.py
ambientmeta/exceptions.py
ambientmeta/models.py
ambientmeta-0.1.0.dist-info/METADATA
ambientmeta-0.1.0.dist-info/WHEEL
ambientmeta-0.1.0.dist-info/top_level.txt
ambientmeta-0.1.0.dist-info/RECORD
