Metadata-Version: 2.4
Name: ambientmeta
Version: 0.1.0
Summary: Python SDK for the AmbientMeta Privacy Gateway — sanitize PII before LLM calls
Author-email: AmbientMeta <hello@ambientmeta.dev>
License: MIT
Project-URL: Homepage, https://ambientmeta.com
Project-URL: Repository, https://github.com/AmbientMeta/ambientmeta-api
Project-URL: Documentation, https://github.com/AmbientMeta/ambientmeta-api/blob/main/docs/quickstart.md
Keywords: pii,privacy,llm,sanitize,redaction
Classifier: Development Status :: 4 - Beta
Classifier: Intended Audience :: Developers
Classifier: Programming Language :: Python :: 3
Classifier: Programming Language :: Python :: 3.9
Classifier: Programming Language :: Python :: 3.10
Classifier: Programming Language :: Python :: 3.11
Classifier: Programming Language :: Python :: 3.12
Classifier: Topic :: Security
Classifier: Topic :: Software Development :: Libraries :: Python Modules
Requires-Python: >=3.9
Requires-Dist: httpx>=0.24.0
Provides-Extra: dev
Requires-Dist: pytest>=8.0.0; extra == "dev"
Requires-Dist: pytest-asyncio>=0.23.0; extra == "dev"
Requires-Dist: respx>=0.21.0; extra == "dev"
